LICENSE
README.rst
pyproject.toml
sage_numerical_interactive_mip/__init__.py
sage_numerical_interactive_mip/clean_dictionary.py
sage_numerical_interactive_mip/interactive_milp_problem.py
sage_numerical_interactive_mip.egg-info/PKG-INFO
sage_numerical_interactive_mip.egg-info/SOURCES.txt
sage_numerical_interactive_mip.egg-info/dependency_links.txt
sage_numerical_interactive_mip.egg-info/requires.txt
sage_numerical_interactive_mip.egg-info/top_level.txt
sage_numerical_interactive_mip/_vendor/interactive_simplex_method.py
sage_numerical_interactive_mip/backends/__init__.py
sage_numerical_interactive_mip/backends/abstract_backend_dictionary.py
sage_numerical_interactive_mip/backends/coin_backend_dictionary.py
sage_numerical_interactive_mip/backends/glpk_backend_dictionary.py