Metadata-Version: 2.1
Name: sage_numerical_interactive_mip
Version: 0.3.0
Summary: Interactive mixed integer linear programming solver
Author: Peijun Xiao, Zeyi Wang, Yuan Zhou
Author-email: Matthias Koeppe <mkoeppe@math.ucdavis.edu>
License: GNU General Public License (GPL) v2 or later
Project-URL: Homepage, https://github.com/passagemath/sage-numerical-interactive-mip
Keywords: milp,linear-programming,optimization
License-File: LICENSE
Requires-Dist: passagemath-polyhedra
Requires-Dist: passagemath-plot
Requires-Dist: passagemath-repl
Requires-Dist: passagemath-flint
Provides-Extra: coin
Requires-Dist: passagemath-polyhedra[coin]; extra == "coin"
Provides-Extra: docs
Requires-Dist: sphinx; extra == "docs"
